token_vision/__init__.py
token_vision/calculator.py
token_vision/models.py
token_vision-0.1.0.dist-info/METADATA
token_vision-0.1.0.dist-info/WHEEL
token_vision-0.1.0.dist-info/licenses/LICENSE
token_vision-0.1.0.dist-info/RECORD
