Metadata-Version: 2.4
Name: token-vision
Version: 0.1.0
Summary: A fast, offline token calculator for images with various AI models (Claude, GPT-4V, Gemini)
Project-URL: Homepage, https://github.com/nerveband/token-vision
Project-URL: Repository, https://github.com/nerveband/token-vision.git
Project-URL: Bug Tracker, https://github.com/nerveband/token-vision/issues
Author: nerveband
License-Expression: MIT
License-File: LICENSE
Keywords: AI,Claude,GPT-4,Gemini,image processing,tokenizer,tokens,vision
Classifier: Development Status :: 3 - Alpha
Classifier: Intended Audience :: Developers
Classifier: License :: OSI Approved :: MIT License
Classifier: Programming Language :: Python :: 3
Classifier: Programming Language :: Python :: 3.8
Classifier: Programming Language :: Python :: 3.9
Classifier: Programming Language :: Python :: 3.10
Classifier: Programming Language :: Python :: 3.11
Requires-Python: >=3.8
Requires-Dist: numpy>=1.24.0
Requires-Dist: pillow>=10.0.0
Provides-Extra: dev
Requires-Dist: black>=23.0.0; extra == 'dev'
Requires-Dist: isort>=5.0.0; extra == 'dev'
Requires-Dist: mypy>=1.0.0; extra == 'dev'
Requires-Dist: pytest-cov>=4.0.0; extra == 'dev'
Requires-Dist: pytest>=7.0.0; extra == 'dev'
Requires-Dist: ruff>=0.1.0; extra == 'dev'
